ilum/__init__.py
ilum/api.py
ilum-6.6.0.dist-info/METADATA
ilum-6.6.0.dist-info/WHEEL
ilum-6.6.0.dist-info/top_level.txt
ilum-6.6.0.dist-info/RECORD
