Metadata-Version: 2.4
Name: ilum
Version: 6.6.0
Summary: Ilum job python API
Author-email: Ilum Labs LLC <info@ilum.cloud>
License-Expression: Apache-2.0
Project-URL: Homepage, https://ilum.cloud
Project-URL: Documentation, https://ilum.cloud/docs/
Project-URL: API Reference, https://ilum.cloud/docs/api/
Project-URL: Roadmap, https://roadmap.ilum.cloud/roadmap
Project-URL: Feature Requests, https://roadmap.ilum.cloud/boards/feature-requests
Project-URL: Tracker, https://roadmap.ilum.cloud/boards/bugs
Classifier: Programming Language :: Python :: 3
Classifier: Operating System :: OS Independent
Requires-Python: >=3.9
